{
  "name": "Louisa Anderson",
  "age": 43,
  "address": {
    "street": "Luposo Boulevard",
    "city": "Saudoked",
    "state": "NY",
    "zip": "13821"
  },
  "contact": {
    "phone": "(249) 600-9413",
    "servicePhone": "800329856"
  },
  "birthday": "1999-10-09T10:24:01.382Z",
  "ip": "59.246.254.226",
  "foo": "bar",
  "profile": {
    "about": "Cu zit kezeni vegogvif waduca siknavdab emahadde ujgol uti wobaom rozanri widji womcad givvo ukuibjeb wunip bendeos bicufdak. Kurhejo bucdo nu zu wiz su roda moci culti zepli kijfabbi azdovroj so. Onegiw nanruk vihduz mar ohhec modali toponi fakmat suzenomin uf ilfafoj huwki. Ra gip gi befad zalto edudug maleguw ehle hole der halku tawuvet. Cuwejwo gi efotipali pupvi timul ki dil salruezi jatje hu jinjen tupek teke dojcigif zuj. Zav saes huvwu ti tonzu ekoza jak ilu anbepera ecerawu laj wuvba poz wos.",
    "bio": "Jeko wuguk no se rur en fad sorab vugi vikoajo ip heror. Di ow giplo obo go fivegeni ho fita empuh bom buupiara eba sicgafwoj puf bugej ahbozi. Cikvasjol fakico iheez pugu nu wog mefuk tahmo osite hod lig pitsefob ni tok zuete as. Go umolefro pueh pesta ofoit ja wibohzic jef cut lo zobawa gaani bugoc zewogu apoluda."
  },
  "apiKey": "3e6b19d59aac4d2e0127ccd98c637736ee964c6cd7ebbd2130ca07f7ceec9261",
  "currency": {
    "code": "ARS",
    "name": "Argentina Peso"
  }
}