{
  "name": "Mike Reese",
  "age": 61,
  "address": {
    "street": "Soztuw Circle",
    "city": "Ebocejas",
    "state": "WA",
    "zip": "99006"
  },
  "contact": {
    "phone": "(429) 742-9951",
    "servicePhone": "800399155"
  },
  "birthday": "1979-09-06T16:07:16.146Z",
  "ip": "165.29.228.181",
  "foo": "bar",
  "profile": {
    "about": "Gefaze ciovo ci hiew aruwu teca iffetsi toig pu fatupa cohoj poc bafeema ofsek apiru afsu. Gubrapnuh hopim taf hufov hejofi maur cedehu guiluena jozec jowwoh devoh pu vavhok kaninra nir lugawis nelma je. Da tum lop errutfe riruog labefid ba hodeke vika romsor iwfak pe. Hijki ribamgu baahi zavivgu sizezo lihuwu cezcik kiko ec reka zar kime dobmu ho fugid hi becolo sa. Jufufose iva pib atuik eleziw bewziw wuul pututu cujod anuihe avazezu tikorzav asakotiw eletehup. Uno pulegeh ibwaiw en pawecar ivuanaker beibafo nusa zob dawe nolle pawnipez losfatsep kom ojo nuri ufoligu etejuguli.",
    "bio": "Semhuvvoh ito ridcufpih dovaon divfuv zoge joc rusbe boduzle jah ic su. Pise fukoum wewpap geldudoh vama do cijcu zuew deta epe dibjulun nam huwlespi lejcoduj fibjir diwdonhol. Jipesepul wan mizipvi morefeg vinak za bezbi hucidus roza busilhot lule urok du. Cuhak visjuz tapbemigo votopto koisoli asmipne gaccachu bigehati vi piamti fadij esukufo. Lufuha tonaw wuwifdeh omilezpih uchapu topul sezbokfo ko gi manmumran ba lo nunjum ce vem dagfijima azipcof."
  },
  "apiKey": "d50e9a531cf914c383b9a5823cc045ed2e9862379b617dd97a8d46ed04b62463",
  "currency": {
    "code": "NGN",
    "name": "Nigeria Naira"
  }
}