{
  "name": "Kevin Martinez",
  "age": 33,
  "address": {
    "street": "Cittic Grove",
    "city": "Listulbug",
    "state": "IL",
    "zip": "18958"
  },
  "contact": {
    "phone": "(888) 608-2423",
    "servicePhone": "800272127"
  },
  "birthday": "2003-05-28T23:47:56.243Z",
  "ip": "233.114.200.167",
  "foo": "bar",
  "profile": {
    "about": "Gih botu izibucdef po veowi we cep teni eceuvi vebgaz zoidgu wa aca izsi gic or. Ruzris min bi kajidiz gevebib acapowu dirumelu dipiwdob fe waev rosa da movohjiv minpe. Ja owze fo jed surbinpi jer ji wozso ugleka turli jipa bifceggeg ece midtudra kamaro hondu gavun nuwenlip. Hut gaer utukig fikume fogeika latoj guv sad helij ifu dav veewejis oga kadwopa igo mihhuun jefuhezec ho. Figa delzol cejjizkav ap fum hegdume wodo muuc kil panru miciv ratdused wojkeam tahahuola fez ujdo folicezu tuw.",
    "bio": "Enori bofa ahufojufi zikewter wukju hanik mevbesol vochoas sijkisfam sefketif pavbijcuj muwced gij duw saz luhwoohe esutow sabvu. Sujpac bihtusva telomja hitam rihucib bonmek pu pavit num fonkis so wokanari. Nugja ajo gi wegtowihi jen vago vu teuku reboce jaepni lom dertenjam uke labjataw donum ketajen. Ganatona lesebbu tu focooha oludapdo ugmem ca esilec ute hocmu ovjoh jeprozit ereino zoj sato couru pu pabuv. Fohtekut jisepred rogub iknulefe se pegiguvo muvpouca okawar ahbam womta ep lakunuh iziacuzo."
  },
  "apiKey": "790438f54e1b7871ec4dab4b9967974f3e63f14ca8e66b853068d95048435cc4",
  "currency": {
    "code": "HKD",
    "name": "Hong Kong Dollar"
  }
}