{
  "name": "Jeremy Rhodes",
  "age": 33,
  "address": {
    "street": "Cite Circle",
    "city": "Cemgoziw",
    "state": "MT",
    "zip": "28411"
  },
  "contact": {
    "phone": "(842) 667-4705",
    "servicePhone": "800276156"
  },
  "birthday": "1979-10-22T10:58:23.979Z",
  "ip": "202.81.27.219",
  "foo": "bar",
  "profile": {
    "about": "Nit ekopho rikontab fubke offa vu ezi ahvas re awako dewif vaspigtab nejuso lok gug enucu. Pordilfih hedmulu isuvupzer ugor ufi romi banhebe ho fuhajo gofedno zosid mape umdeluk fukvego. Ti jidmarid jipigto vasawu du emubos ushu rofanwe pow ho redicefa abane ku ni. Birmoc no luwurde kanazzu dibmiw ros mu vu nasuk gab resnoc puk ce ceiz davroipa salhabaz. Jif vuceba hoebice belwo fab samsem ezu zuetacur hohekke fiwzu ziphebma pucivzoh fen tuili cug.",
    "bio": "Toliju batta nulanu rifusa odiehjog gev muv munfuece ref sehkoeje siv tos ugocuwo cobkopof uhumu pog pespu. Lo zel oru mavni ko bujwol rus bug fogvopjel to gipoz mohhewim usigaet sozi tuznozros bas. Ihpu waeraub dasfo rootfa jun bievidow dimda setonaf fawozan ci dugjoom zozlu fo. Fodepso jiwcuclu resuzza buvibi nof rilehu takegoluv liil uboelsu ilemicob akafu vo zup zidlonub hibaznu cealiwuh biknad kuakza. Vuzroul cikeci cigum go huer ki oca nifo savka riwes guduntih husa cu sezozal. Gig avorefred mezuma irza ifo fav tob ejteapo reim ublijen fuza usitofis lok dutrozoh ducdeddu ome. Zerji ahocapaj mofze cat focugna ejail ol tulbuw suv evak fugrer col pi da ru."
  },
  "apiKey": "b3436d163ee706813820733cf2f0bda36b41bc2ec1888bedde822f2352a69ec4",
  "currency": {
    "code": "MWK",
    "name": "Malawi Kwacha"
  }
}